{"id":"-648774411605978005","age":65,"gender":"M","taxonomy":"2085R0202X","emr":"Cpt  70450, modifiers  26, icds","note":"\\r\\n================================================================================\\r\\n\\r\\n                              UT MEDICAL CENTER\\r\\n\\r\\nPatient Name: STEPHEN A BOUNDS\\r\\nBirth Date: 09/27/1957\\r\\n\\r\\nReferring Doctor: THAKKAR, ASHISH R\\r\\nReading Doctor: ELLINGTON, CHRISTOPHER R\\r\\nVisit No.: 6776240031\\r\\nOrder No.: 6038831447\\r\\nExam Date: 03/18/2023 22:10:00\\r\\nExam: 70450 - CT Head Without IV Contrast 70450\\r\\n================================================================================\\r\\n\\r\\nDOB: 09/27/1957\\r\\nHistory Number:677624\\r\\nEXAM: CT Head Without IV Contrast 70450\\n\\nINDICATION:fall, found down   \\n\\nTECHNIQUE: Helical CT of the head was obtained without intravenous contrast. Axial, coronal and sagittal images were created.\\n\\nDose reduction technique was used including one or more of the following: automated exposure control, adjustment of mA and kV according to patient size, and/or iterative reconstruction.\\n\\nCOMPARISON: None. \\n\\nFINDINGS:\\n\\nQuality: Average.  No unusual artifacts beyond the limitations of routine CT.\\n\\nINTRACRANIAL:\\nHemorrhage: None.\\nMass effect: None.\\nBrain parenchyma: Moderate generalized cerebral and cerebellar volume loss. Mild nonspecific periventricular hypoattenuation is most consistent with chronic small vessel ischemic disease.\\nVentricles: Reflect volume loss.\\nOther: None.\\n\\nCRANIAL/EXTRACRANIAL:\\nBony structures: No depressed or displaced skull fractures.\\nParanasal sinuses and mastoid air cells: Sphenoid sinus mucosal thickening.\\nVisualized orbits: The imaged portions appear normal.\\nOther: Noncontributory.\\n\\nIMPRESSION:\\n\\n1.   No acute intracranial findings.\\n\\n\\nPLAT-50-177\\r\\n\\r\\nPOSS GI BLEED\\r\\n)"}
{"id":"-3626090299906748300","age":43,"gender":"F","taxonomy":"radiology","emr":"Cpt  73030, modifiers  26, icds","note":"\\r\\n================================================================================\\r\\n\\r\\n                              BAPTIST HEALTH RICHMOND\\r\\n\\r\\nPatient Name: CRYSTAL L WILLIS\\r\\nBirth Date: 07/04/1976\\r\\n\\r\\nReferring Doctor: SOWDEN, KIMBERLY H\\r\\nReading Doctor: KOSTELIC, JON K\\r\\nVisit No.: 200001268763\\r\\nOrder No.: 2003775845\\r\\nExam Date: 09/12/2019 16:39:00\\r\\nExam: 73030 - XR SHOULDER 2+ VW LEFT\\r\\n================================================================================\\r\\n\\r\\nMRN  E48409\\r\\nPatient Name  Willis,Crystal L\\r\\nFIN  200001268763\\r\\nGender  Female\\r\\nDOB  07/04/1976\\r\\nEncounter Type  Outpatient\\r\\nFacility  Baptist Health Richmond\\r\\nNurse Unit\\r\\nExam Room  BH RIC XRAY\\r\\nAccession Nbr  2003775845\\r\\nOrder id  2003775845\\r\\nParent/Child\\r\\nProcedure  XR SHOULDER 2+ VW LEFT\\r\\nOrder Doc  Sowden, Kimberly H\\r\\nDoc NPI\\r\\nExam Completion Date 09/12/19 16:39\\r\\nReport\\r\\nFINAL REPORT\\r\\nCLINICAL HISTORY:\\r\\n. PAIN\\r\\nFINDINGS:\\r\\n3 views of the left shoulder were obtained. There is no acute\\r\\nfracture or dislocation. The joint spaces are intact. There are\\r\\nno soft tissue abnormalities.\\r\\nNo acute process.\\r\\nAuthenticated by Jon K. Kostelic, MD on 09/12/2019 04:49:56 PM\\r\\nTranscriptionist: \\r\\nDictated by:\\r\\nDictation Date: 09/12/2019\\r\\nInterpreted & Released By: Kostelic, Jon K, MD\\r\\nReleased Date Time: 09/12/2019 16:49\\r\\n)"}
{"id":"-2637484990438540170","age":81,"gender":"M","taxonomy":"radiology","emr":"Cpt  77012, modifiers  26, icds","note":"\\r\\n================================================================================\\r\\n\\r\\n                              MARY LANNING HEALTHCARE\\r\\n\\r\\nPatient Name: Frank L Husted\\r\\nBirth Date: 08/10/1937\\r\\nSSN: 110-28-0514\\r\\nReferring Doctor: BELL, SCOTT \\r\\nReading Doctor: Rodriguez, Paul \\r\\nVisit No.: 3100617054\\r\\nOrder No.: RD0753055\\r\\nExam Date: 07/28/2019 00:00:00\\r\\nExam: 49406 - CT image guided fluid collection\\r\\n================================================================================\\r\\n\\r\\n1.  Completed CT-guided lower neck fluid aspiration.\\r\\nTYPE OF STUDY:  CT IMAGE GUIDED FLUID COLLECTION INDICATION:  aspirate abscess DISCUSSION:  Informed consent was obtained. The patient has a lower posterior neck fluid collection. He has had recent cervical spine fusion surgery. CT was used to localize a fluid collection. The neck was prepped and draped in usual sterile fashion. 1% lidocaine was used for local anesthesia. A 20-gauge was advanced into the fluid collection near the tip of the spinous process. Imaging showed good position. Approximate 5 mL of light red fluid was aspirated. This was sent to the laboratory for analysis. Needle was removed. No complications occurred. [CT individualized dose optimization technique was used to include one or more of the following techniques: automated exposure control, mA and /or kV dose modulation according to patient size, and/or iterative reconstructive technique.] [MIP technique was done for 2D and/or 3D rendering.]\\r\\n\\r\\nElectronically Signed By: Rodriguez, Paul\\r\\nSigned Date: 07/28/2019 5:16 PM CDT)"}
{"id":"-1622930769126638165","age":76,"gender":"F","taxonomy":"radiology","emr":"Cpt  77067, modifiers  26, icds","note":"\\r\\n================================================================================\\r\\n\\r\\n                              BAXTER REGIONAL MEDICAL CNTR\\r\\n\\r\\nPatient Name: ALICE ANNE RAGLAND\\r\\nBirth Date: 04/26/1943\\r\\n\\r\\nReferring Doctor: LANGER, NEIL I\\r\\nReading Doctor: WILSON, MATTHEW B\\r\\nVisit No.: 62830293\\r\\nOrder No.: 681899897\\r\\nExam Date: 03/10/2020 13:27:00\\r\\nExam: 71045 - MMU Screen Tomo Bil w/CAD\\r\\n================================================================================\\r\\n\\r\\nDepartment: OPO\\r\\nReason For Exam: screening\\r\\n\\r\\nMMU Screen Tomo Bil w/CAD\\r\\n\\r\\nBilateral screening mammograms with tomosynthesis and CAD imaging.\\r\\n\\r\\nComparison:    10/20/2015\\r\\n\\r\\nFindings: There are scattered areas of fibroglandular density. No\\r\\nsuspicious masses, suspicious calcifications, areas of architectural\\r\\ndistortion or secondary signs of malignancy are seen.\\r\\n\\r\\nImpression:\\r\\n1. BI-RADS 2 (benign findings).\\r\\n2. No evidence of malignancy is seen.\\r\\n3. Note: A negative mammogram should not preclude further evaluation\\r\\nof a clinically suspicious abnormality.\\r\\n4. Recommend routine bilateral screening mammograms in one year.\\r\\n\\r\\nBaxter Regional Medical Center generates a yearly reminder letter for\\r\\nscreening mammograms.\\r\\n\\r\\n\\r\\n\\r\\n\\r\\n\\r\\n\\r\\n)"}
